pangea_anthropic/__init__.py
pangea_anthropic/_client.py
pangea_anthropic/_exceptions.py
pangea_anthropic/_resource.py
pangea_anthropic/py.typed
pangea_anthropic/resources/messages/__init__.py
pangea_anthropic/resources/messages/messages.py
pangea_anthropic-0.1.1.dist-info/WHEEL
pangea_anthropic-0.1.1.dist-info/METADATA
pangea_anthropic-0.1.1.dist-info/RECORD
