Metadata-Version: 2.4
Name: pangea-anthropic
Version: 0.1.1
Summary: A wrapper around the Anthropic Python library
Author: Pangea
Author-email: Pangea <support@pangea.cloud>
License-Expression: MIT
Requires-Dist: anthropic>=0.66.0
Requires-Dist: anyio>=4.10.0
Requires-Dist: httpx>=0.28.1
Requires-Dist: pangea-sdk>=6.6.0
Requires-Dist: typing-extensions>=4.15.0
Requires-Python: >=3.10
